freezedry.py
freezedry-1.0.0.dist-info/METADATA
freezedry-1.0.0.dist-info/WHEEL
freezedry-1.0.0.dist-info/licenses/LICENSE
freezedry-1.0.0.dist-info/RECORD
