Metadata-Version: 2.4
Name: freezedry
Version: 1.0.0
Summary: A simple package to save a compressed directory
Project-URL: Homepage, https://github.com/landoskape/freezedry
Project-URL: Documentation, https://freezedry.readthedocs.io/en/stable/
Author-email: Andrew Landau <andrew+tyler+landau+getridofthisanddtheplusses@gmail.com>
License: MIT
License-File: LICENSE
Keywords: compress,compression,python code
Classifier: Development Status :: 4 - Beta
Classifier: Intended Audience :: Developers
Classifier: License :: OSI Approved :: MIT License
Classifier: Operating System :: OS Independent
Classifier: Programming Language :: Python :: 3.7
Classifier: Programming Language :: Python :: 3.8
Classifier: Programming Language :: Python :: 3.9
Classifier: Programming Language :: Python :: 3.10
Classifier: Programming Language :: Python :: 3.11
Classifier: Programming Language :: Python :: 3.12
Classifier: Programming Language :: Python :: 3.13
Requires-Python: >=3.7
Requires-Dist: gitignore-parser
Provides-Extra: test
Requires-Dist: pytest-cov>=4.0.0; extra == 'test'
Requires-Dist: pytest>=7.0.0; extra == 'test'
